imgmanip/__main__.py
imgmanip/config.py
imgmanip/dialogs/confirm_dialog.py
imgmanip/dialogs/info_dialog.py
imgmanip/dialogs/new_task_dialog.py
imgmanip/dialogs/preferences_dialog.py
imgmanip/dialogs/rename_dialog.py
imgmanip/dialogs/sort_images_dialog.py
imgmanip/functions/check_image.py
imgmanip/functions/create_time_str.py
imgmanip/functions/file_size.py
imgmanip/functions/get_ext.py
imgmanip/functions/run_tasks.py
imgmanip/functions/save_img.py
imgmanip/functions/tasks/color_detection.py
imgmanip/functions/tasks/compress.py
imgmanip/functions/tasks/convert.py
imgmanip/functions/tasks/convert_color_mode.py
imgmanip/functions/tasks/flip.py
imgmanip/functions/tasks/invert.py
imgmanip/functions/tasks/resize.py
imgmanip/logs.py
imgmanip/main.py
imgmanip/models/axis.py
imgmanip/models/color_mode.py
imgmanip/models/image_extension.py
imgmanip/models/resize_type.py
imgmanip/models/save_type.py
imgmanip/models/sort.py
imgmanip/models/task.py
imgmanip/widgets/horizontal_line.py
imgmanip/widgets/main/center_part.py
imgmanip/widgets/main/left_part.py
imgmanip/widgets/main/right_part.py
imgmanip/widgets/main_screen.py
imgmanip/widgets/task_frames/color_detection_task_frame.py
imgmanip/widgets/task_frames/compress_task_frame.py
imgmanip/widgets/task_frames/convert_color_mode_task_frame.py
imgmanip/widgets/task_frames/convert_task_frame.py
imgmanip/widgets/task_frames/flip_task_frame.py
imgmanip/widgets/task_frames/invert_task_frame.py
imgmanip/widgets/task_frames/resize_task_frame.py
imgmanip-0.0.6.dist-info/entry_points.txt
imgmanip-0.0.6.dist-info/LICENSE
imgmanip-0.0.6.dist-info/WHEEL
imgmanip-0.0.6.dist-info/METADATA
imgmanip-0.0.6.dist-info/RECORD
