Metadata-Version: 2.1
Name: imgmanip
Version: 0.0.6
Summary: Image manipulation tool written in python in which you can select a large number of photos and perform a lot of different operations on them.
License: MIT
Author: Mikołaj Badyl
Author-email: contact@hawier.dev
Requires-Python: >=3.8,<3.11
Classifier: License :: OSI Approved :: MIT License
Classifier: Programming Language :: Python :: 3
Classifier: Programming Language :: Python :: 3.8
Classifier: Programming Language :: Python :: 3.9
Classifier: Programming Language :: Python :: 3.10
Requires-Dist: Pillow (>=9.2.0,<10.0.0)
Requires-Dist: PySide6 (>=6.3.2,<7.0.0)
Requires-Dist: PyYAML (>=6.0,<7.0)
Requires-Dist: natsort (>=8.2.0,<9.0.0)
Requires-Dist: numpy (>=1.23.3,<2.0.0)
Requires-Dist: opencv-python (>=4.6.0.66,<5.0.0.0)
Requires-Dist: pyexiv2 (>=2.8.0,<3.0.0)
Requires-Dist: pyperclip (>=1.8.2,<2.0.0)
Requires-Dist: pyqtdarktheme (>=1.1.0,<2.0.0)
